extmath/__init__.py
extmath/basic.py
extmath/meta.py
extmath/number_theory.py
extmath-0.9.2.dist-info/LICENSE.md
extmath-0.9.2.dist-info/METADATA
extmath-0.9.2.dist-info/WHEEL
extmath-0.9.2.dist-info/top_level.txt
extmath-0.9.2.dist-info/RECORD
