Metadata-Version: 2.1
Name: extmath
Version: 0.9.2
Summary: Collections of useful tools in mathematics.
Home-page: https://github.com/neizod/extmath
Author: Nattawut Phetmak
Author-email: neizod@gmail.com
License: MIT
Platform: UNKNOWN
Classifier: Programming Language :: Python :: 3
Classifier: License :: OSI Approved :: MIT License
Classifier: Operating System :: OS Independent
